odoo10_addon_l10n_it_withholding_tax_payment-10.0.2.0.0-nspkg.pth
odoo/addons/l10n_it_withholding_tax_payment/README.rst
odoo/addons/l10n_it_withholding_tax_payment/__init__.py
odoo/addons/l10n_it_withholding_tax_payment/__manifest__.py
odoo/addons/l10n_it_withholding_tax_payment/workflow.xml
odoo/addons/l10n_it_withholding_tax_payment/data/sequence.xml
odoo/addons/l10n_it_withholding_tax_payment/i18n/am.po
odoo/addons/l10n_it_withholding_tax_payment/i18n/ar.po
odoo/addons/l10n_it_withholding_tax_payment/i18n/bg.po
odoo/addons/l10n_it_withholding_tax_payment/i18n/bs.po
odoo/addons/l10n_it_withholding_tax_payment/i18n/ca.po
odoo/addons/l10n_it_withholding_tax_payment/i18n/ca_ES.po
odoo/addons/l10n_it_withholding_tax_payment/i18n/cs.po
odoo/addons/l10n_it_withholding_tax_payment/i18n/da.po
odoo/addons/l10n_it_withholding_tax_payment/i18n/de.po
odoo/addons/l10n_it_withholding_tax_payment/i18n/el_GR.po
odoo/addons/l10n_it_withholding_tax_payment/i18n/en_AU.po
odoo/addons/l10n_it_withholding_tax_payment/i18n/en_GB.po
odoo/addons/l10n_it_withholding_tax_payment/i18n/es.po
odoo/addons/l10n_it_withholding_tax_payment/i18n/es_AR.po
odoo/addons/l10n_it_withholding_tax_payment/i18n/es_CL.po
odoo/addons/l10n_it_withholding_tax_payment/i18n/es_CO.po
odoo/addons/l10n_it_withholding_tax_payment/i18n/es_CR.po
odoo/addons/l10n_it_withholding_tax_payment/i18n/es_DO.po
odoo/addons/l10n_it_withholding_tax_payment/i18n/es_EC.po
odoo/addons/l10n_it_withholding_tax_payment/i18n/es_ES.po
odoo/addons/l10n_it_withholding_tax_payment/i18n/es_MX.po
odoo/addons/l10n_it_withholding_tax_payment/i18n/es_PE.po
odoo/addons/l10n_it_withholding_tax_payment/i18n/es_PY.po
odoo/addons/l10n_it_withholding_tax_payment/i18n/es_VE.po
odoo/addons/l10n_it_withholding_tax_payment/i18n/et.po
odoo/addons/l10n_it_withholding_tax_payment/i18n/eu.po
odoo/addons/l10n_it_withholding_tax_payment/i18n/fa.po
odoo/addons/l10n_it_withholding_tax_payment/i18n/fi.po
odoo/addons/l10n_it_withholding_tax_payment/i18n/fr.po
odoo10_addon_l10n_it_withholding_tax_payment-10.0.2.0.0.dist-info/METADATA
odoo10_addon_l10n_it_withholding_tax_payment-10.0.2.0.0.dist-info/WHEEL
odoo10_addon_l10n_it_withholding_tax_payment-10.0.2.0.0.dist-info/namespace_packages.txt
odoo10_addon_l10n_it_withholding_tax_payment-10.0.2.0.0.dist-info/top_level.txt
odoo10_addon_l10n_it_withholding_tax_payment-10.0.2.0.0.dist-info/RECORD
