Metadata-Version: 2.1
Name: odoo10-addon-l10n-it-withholding-tax-payment
Version: 10.0.2.0.0
Summary: Italian Withholding Tax Payment
Home-page: https://odoo-community.org/
Author: Openforce, Odoo Italia Network, Odoo Community Association (OCA)
Author-email: support@odoo-community.org
License: AGPL-3
Platform: UNKNOWN
Classifier: Programming Language :: Python
Classifier: Framework :: Odoo
Classifier: License :: OSI Approved :: GNU Affero General Public License v3
Requires-Python: ~=2.7
Requires-Dist: odoo10-addon-l10n-it-withholding-tax
Requires-Dist: odoo (<10.1dev,>=10.0)
